oneneuron/__init__.py
oneneuron/perceptron.py
OneNeuron_pypi_deepakchothe20-0.0.2.dist-info/LICENSE
OneNeuron_pypi_deepakchothe20-0.0.2.dist-info/METADATA
OneNeuron_pypi_deepakchothe20-0.0.2.dist-info/WHEEL
OneNeuron_pypi_deepakchothe20-0.0.2.dist-info/top_level.txt
OneNeuron_pypi_deepakchothe20-0.0.2.dist-info/RECORD
