Metadata-Version: 2.1
Name: OneNeuron-pypi-deepakchothe20
Version: 0.0.2
Summary: its an implimentation of Perceptron
Home-page: https://github.com/deepakchothe20/OneNeuron_pypi
Author: deepakchothe20
Author-email: deepakchothe1998@gmail.com
Project-URL: Bug Tracker, https://github.com/deepakchothe20/OneNeuron_pypi/issues
Classifier: Programming Language :: Python :: 3
Classifier: License :: OSI Approved :: MIT License
Classifier: Operating System :: OS Independent
Requires-Python: >=3.7
License-File: LICENSE
Requires-Dist: numpy
Requires-Dist: tqdm
